pythonpixels/__init__.py
pythonpixels/pythonpixel.py
pythonpixels-1.2.14.dist-info/LICENSE
pythonpixels-1.2.14.dist-info/METADATA
pythonpixels-1.2.14.dist-info/WHEEL
pythonpixels-1.2.14.dist-info/top_level.txt
pythonpixels-1.2.14.dist-info/RECORD
