Metadata-Version: 2.1
Name: pythonpixels
Version: 1.2.14
Summary: An API wrapper for the python discord pixels project
Home-page: https://github.com/sebkuip/pythonpixels
Author: sebkuip
Author-email: sebkuip@tekx.it
License: MIT
Keywords: API
Platform: UNKNOWN
Classifier: Programming Language :: Python :: 3
Classifier: License :: OSI Approved :: MIT License
Classifier: Operating System :: OS Independent
Classifier: Development Status :: 4 - Beta
Classifier: Intended Audience :: Developers
License-File: LICENSE
Requires-Dist: pillow
Requires-Dist: rich
